directory_structure_generator/__init__.py
directory_structure_generator/__main__.py
directory_structure_generator/colors.py
directory_structure_generator/generator.py
directory_structure_generator/icons.py
directory_structure_generator/run.py
directory_structure_generator/utils.py
directory_structure_generator-1.0.2.dist-info/LICENSE
directory_structure_generator-1.0.2.dist-info/METADATA
directory_structure_generator-1.0.2.dist-info/WHEEL
directory_structure_generator-1.0.2.dist-info/entry_points.txt
directory_structure_generator-1.0.2.dist-info/top_level.txt
directory_structure_generator-1.0.2.dist-info/RECORD
