Metadata-Version: 2.1
Name: directory_structure_generator
Version: 1.0.2
Summary: This script is used to generate a list of the project structure in a markdown format. It is useful for README.md files.
Home-page: https://github.com/7oSkaaa/directory_structure_generator
Author: Ahmed Hossam
Author-email: ahmed.7oskaa@gmail.com
Classifier: Programming Language :: Python :: 3
Classifier: License :: OSI Approved :: MIT License
Classifier: Operating System :: OS Independent
Requires-Python: >=3.6
License-File: LICENSE
Requires-Dist: argparse
